[[[3],[{"rank":7,"label":"Full House","value":[11,6],"cards":[26,24,37,45,18,6,19],"faceValues":["As","Qd","Qs","7c","6d","7h","7d"],"straight":-1,"suit":-1,"flush":-1,"groups":{"nominals":[[26],[],[],[],[],[18],[45,6,19],[],[],[],[],[24,37],[]],"suits":[[6],[24,18,19],[26,37],[45]],"collections":[[5,13],[11],[6],[]]},"position":3},{"rank":7,"label":"Full House","value":[5,6],"cards":[28,31,37,45,18,6,19],"faceValues":["3s","6s","Qs","7c","6d","7h","7d"],"straight":-1,"suit":-1,"flush":-1,"groups":{"nominals":[[],[],[28],[],[],[31,18],[45,6,19],[],[],[],[],[37],[]],"suits":[[6],[18,19],[28,31,37],[45]],"collections":[[2,11],[5],[6],[]]},"position":4},{"rank":4,"label":"Three of a Kind","value":[11,12,6],"cards":[12,42,37,45,18,6,19],"faceValues":["Kh","4c","Qs","7c","6d","7h","7d"],"straight":-1,"suit":-1,"flush":-1,"groups":{"nominals":[[],[],[],[42],[],[18],[45,6,19],[],[],[],[],[37],[12]],"suits":[[12,6],[18,19],[37],[42,45]],"collections":[[3,5,11,12],[],[6],[]]},"position":1},{"rank":4,"label":"Three of a Kind","value":[7,11,6],"cards":[17,33,37,45,18,6,19],"faceValues":["5d","8s","Qs","7c","6d","7h","7d"],"straight":-1,"suit":-1,"flush":-1,"groups":{"nominals":[[],[],[],[],[17],[18],[45,6,19],[33],[],[],[],[37],[]],"suits":[[6],[17,18,19],[33,37],[45]],"collections":[[4,5,7,11],[],[6],[]]},"position":2},{"rank":4,"label":"Three of a Kind","value":[7,11,6],"cards":[7,2,37,45,18,6,19],"faceValues":["8h","3h","Qs","7c","6d","7h","7d"],"straight":-1,"suit":-1,"flush":-1,"groups":{"nominals":[[],[],[2],[],[],[18],[45,6,19],[7],[],[],[],[37],[]],"suits":[[7,2,6],[18,19],[37],[45]],"collections":[[2,5,7,11],[],[6],[]]},"position":5},{"rank":4,"label":"Three of a Kind","value":[5,11,6],"cards":[1,15,37,45,18,6,19],"faceValues":["2h","3d","Qs","7c","6d","7h","7d"],"straight":-1,"suit":-1,"flush":-1,"groups":{"nominals":[[],[1],[15],[],[],[18],[45,6,19],[],[],[],[],[37],[]],"suits":[[1,6],[15,18,19],[37],[45]],"collections":[[1,2,5,11],[],[6],[]]},"position":0}]]]
